{
  "dinner": {
    "weeks": {
      "Week 1": {
        "days": {
          "Monday": {
            "Appetizer 1": "Corn Soup",
            "Appetizer 2": "CITRUS AND SHRIMP LEMON LAVENDER CUPS",
            "Elevated": "Braised Short Ribs with Red Wine Sauce",
            "Comfort": "",
            "Alternative": "Pan Seared Salmon with Cucumber Dill Yogurt Sauce",
            "Veggie 1": "GARLIC GREEN BEANS",
            "Veggie 2": "HONEY GLAZED CARROTS",
            "Starch": "ROASTED BABY POTATOES",
            "Dessert": "PEACH MELBA                                  (GF)"
          },
          "Tuesday": {
            "Appetizer 1": "CALIFORNIA BROCOCLI SALAD",
            "Appetizer 2": "CHICKEN VEGETABLE IN BROTH",
            "Elevated": "CARVED PORK TENDERLOIN WITH APPLE&FENNEL SLAW (GF/DF)",
            "Comfort": "TURKEY MEDALLION WITH CRANBERRY&ORANGE CHUTNEY                  (GF/DF)",
            "Alternative": "SAUTEED SHRIMP WITH GARLIC, WHITE WINE & FRESH DICED TOMATO (GF/DF)",
            "Veggie 1": "GRILLED ASPARAGUS",
            "Veggie 2": "BUTTERED PEAS",
            "Starch": "WILD RICE PILAF",
            "Dessert": "CHOCOLATE MOUSSE WITH SPONGE TOFFEE         (GF)"
          },
          "Wednesday": {
            "Appetizer 1": "PROSCIUTTO WRAPPED PEARS WITH ARUGULA",
            "Appetizer 2": "FRIED CALAMARI WITH SMOKED PAPRIKA DIP",
            "Elevated": "Roast Beef with Chimichurri",
            "Comfort": "HERB ROASTED CHICKEN LEG WITH LEMON SAUCE (GF/DF)",
            "Alternative": "BAKED COD WITH LEMON CAPER VINAIGRETTE (GF/DF)",
            "Veggie 1": "GRILLED SUMMER ZUCCHINI",
            "Veggie 2": "ROASTED BUTTERNUT",
            "Starch": "QUINOA PILAF",
            "Dessert": "LEMON CURD TART WITH EGG WHITE"
          },
          "Thursday": {
            "Appetizer 1": "ANTIPASTI SKEWERS",
            "Appetizer 2": "CREAM OF CARROT SOUP",
            "Elevated": "SEARED SCALLOPS WITH CITRUS & HERB SALSA   (GF/DF)",
            "Comfort": "ROASTED LAMB LEG WITH MINT GREMOLATA           (GF/DF)",
            "Alternative": "GRILLED CHICKEN BREAST WITH BASIL PESTO AND ROASTED TOMATO         (GF)",
            "Veggie 1": "SAUTEED SPINACH WITH DICED ONIONS",
            "Veggie 2": "ROASTED CARROTS WITH CARDAMON SEASONING",
            "Starch": "COUSCOUS WITH FRESH CHOPPED HERBS",
            "Dessert": "RICE PUDDING WITH FRESH BERRIES                  (GF/DF)"
          },
          "Friday": {
            "Appetizer 1": "SOPA AJOBLANCO",
            "Appetizer 2": "WHALDORF ENDIVE SALAD",
            "Elevated": "BEEF STRIPS WITH SAUTEED WILD MUSHROOMS WITH PAN SAUCE                                         (GF)",
            "Comfort": "ROASTED TURKEY BREAST WITH PAN GRAVY           (GF)",
            "Alternative": "BAKED HADDOCK WITH TOMATO&BASIL SALSA   (GF/DF)",
            "Veggie 1": "STEAMED BROCCOLI",
            "Veggie 2": "ROASTED PARSNIPS WITH CINNAMON SUGAR",
            "Starch": "FRESH HERB ORZO",
            "Dessert": "ASSORTED DESSERTS"
          },
          "Saturday": {
            "Appetizer 1": "ASIAN VEGETABLE - BEEF SOUP",
            "Appetizer 2": "SHRIMP TEMPURA WITH DIPPING SAUCE",
            "Elevated": "ROASTED PORK WITH GRAINY DIJON MUSTARD SAUCE                                 (GF/DF)",
            "Comfort": "HONEY GARLIC CHICKEN BREAST",
            "Alternative": "GRILLED SHIRMP WITH MANGO SALSA",
            "Veggie 1": "BUTTERED CORN KERNELS",
            "Veggie 2": "ROASTED BRUSSEL SPROUTS",
            "Starch": "BAKED POTATO WITH SOUR CREAM&CHIVE        (GF)",
            "Dessert": "CHEESECAKE WITH BERRY COMPOTE"
          },
          "Sunday": {
            "Appetizer 1": "TACO SOUP",
            "Appetizer 2": "WEDGE SALAD SKEWER",
            "Elevated": "PRIME RIB WITH HORSERADISH YOGURT SAUCE (ON SIDE)      (GF/DF)",
            "Comfort": "POACHED SALMON WITH CUCUMBER&HERB SAUCE",
            "Alternative": "ROASTED CHICKEN WITH THYME&LEMON JUS",
            "Veggie 1": "GREEN BEAN ALMONDINE",
            "Veggie 2": "ROASTED ROOT VEGETABLES (CARROT/YAM/PARSNIP/TURNIP)",
            "Starch": "BUTTER MASHED POTATOES                               (GF)",
            "Dessert": "APPLE PIE"
          }
        }
      },
      "Week 2": {
        "days": {
          "Monday": {
            "Appetizer 1": "COCONUT SHRIMP WITH LIME DIP",
            "Appetizer 2": "CARROT AND ORANGE SOUP",
            "Elevated": "MAPLE GLAZED SALMON FILET WITH",
            "Comfort": "CHICKEN CORDON BLEU",
            "Alternative": "ROAST CHICKEN WITH PAPRIKA",
            "Veggie 1": "STEAMED CAULIFLOWER FLORETS",
            "Veggie 2": "STEAMED CARROTS",
            "Starch": "BAKED FARRO PILAF",
            "Dessert": "BLACK FOREST CAKE"
          },
          "Tuesday": {
            "Appetizer 1": "ROASTED RED PEPPER HUMMUS AND PITA",
            "Appetizer 2": "SPICY TUNA AND CRISPY RICE CRACKER",
            "Elevated": "SEARED HALIBUT WITH CHERRY TOMATO&OLIVE",
            "Comfort": "PASTA WITH SUMMER VEGETABLES WITH LEMON PARMESAN SAUCE",
            "Alternative": "",
            "Veggie 1": "GRILLED ASPARAGUS",
            "Veggie 2": "ROASTED MUSHROOMS",
            "Starch": "WILD RICE",
            "Dessert": "PEACH FRIED PIES"
          },
          "Wednesday": {
            "Appetizer 1": "SHAVED FENNEL AND ORANGE SALAD",
            "Appetizer 2": "CUCUMBER AND DILL SALAD",
            "Elevated": "CHICKEN MARSALA IN MUSHROOM SAUCE",
            "Comfort": "OPEN FACED ROAST BEEF DIP",
            "Alternative": "LEMON BAKED COD",
            "Veggie 1": "SAUTEED SPINACH WITH DICED ONIONS",
            "Veggie 2": "ROASTED BABY TOP CARROTS",
            "Starch": "GARLIC MASHED POTATOES",
            "Dessert": "BANANA CREAM PIE"
          },
          "Thursday": {
            "Appetizer 1": "CORN CHOWDER",
            "Appetizer 2": "MANGO AND AVOCADO SALAD",
            "Elevated": "VEAL SHANK WITH NATURAL JUS",
            "Comfort": "CHICKEN PARMESAN",
            "Alternative": "SEARED SCALLOPS WITH SQUASH PUREE",
            "Veggie 1": "ROASTED ZUCCHINI CHUNKS",
            "Veggie 2": "BUTTERED PEAS",
            "Starch": "ANCIENT GRAINS",
            "Dessert": "ASSORTED DESSERTS"
          },
          "Friday": {
            "Appetizer 1": "SMOKED SALMON CUCUMBER BITES",
            "Appetizer 2": "GAZPACHO SOUP",
            "Elevated": "TURKEY ROULADE WITH SPINACH&SUNDRIED TOMATO                     (GF/DF)",
            "Comfort": "SPAGHETTI AND MEATBALLS IN MARINARA",
            "Alternative": "GRILLED TILAPIA WITH BALSAMIC ONION SAUCE",
            "Veggie 1": "BROCCOLINI WITH GARLIC CONFIT",
            "Veggie 2": "SUMAC SPICED ROASTED CARROT CHUNKS",
            "Starch": "HERB AND CREAM CHEESE POLENTA",
            "Dessert": "LEMON BREAD WITH ICING"
          },
          "Saturday": {
            "Appetizer 1": "GRILLED ZUCCHINI ROLLUP WITH RICOTTA",
            "Appetizer 2": "BACON AND CLAM FLATBREAD",
            "Elevated": "RED WINE BRAISED BEEF BRISKET",
            "Comfort": "ROASTED PORK TENDERLOIN WITH OLIVE AND FETA SALSA",
            "Alternative": "WILD MUSHROOM TART WITH GOAT CHEESE",
            "Veggie 1": "ROASTED MEXICAN STREET CORN",
            "Veggie 2": "BRAISED BEAN CASSOULET",
            "Starch": "HERB ROASTED POTATO WEDGES",
            "Dessert": "KEY LIME PIE"
          },
          "Sunday": {
            "Appetizer 1": "ZUCCHINI FRITTERS WITH DIP",
            "Appetizer 2": "SOBA NOODLE SALAD",
            "Elevated": "SHRIMP LINGUINI WITH SAFFRON SAUCE AND PEPPERED GREENS",
            "Comfort": "ROASTED CHICKEN BREAST IN CREAMY SUNDRIED TOMATO SAUCE",
            "Alternative": "SEARED SALMON WITH BASIL PESTO SAUCE",
            "Veggie 1": "SAUTEED ASPARAGUS (2\" CUTS)",
            "Veggie 2": "ROASTED BUTTERNUT SQUASH",
            "Starch": "WILD RICE PILAF",
            "Dessert": "PEACH COBBLER"
          }
        }
      },
      "Week 3": {
        "days": {
          "Monday": {
            "Appetizer 1": "GERMAN POTATO SALAD",
            "Appetizer 2": "CHILLED MELON SOUP WITH PROSCIUTTO CHIP",
            "Elevated": "SHRIMP CURRY",
            "Comfort": "BAKED CHICKEN IN CREAMY BASIL AND CORN SAUCE",
            "Alternative": "SEARED SALMON FILET WITH PINEAPPLE SALSA",
            "Veggie 1": "SAUTEED BOK CHOY",
            "Veggie 2": "ROASTED CARROTS",
            "Starch": "SCALLOPED POTATOES",
            "Dessert": "ORANGE CUSTARD WITH BLACKBERRY"
          },
          "Tuesday": {
            "Appetizer 1": "AVGOLEMONO SOUP (GREEK LEMON CHICKEN)",
            "Appetizer 2": "SPINACH STRAWBERRY SALAD WITH ALMOND & GOAT CHEESE HONEY MUSTARD DRESSING",
            "Elevated": "BEEF BRISKET BBQ",
            "Comfort": "FRIED CHICKEN",
            "Alternative": "",
            "Veggie 1": "STEAMED BROCCOLI",
            "Veggie 2": "GREEN AND YELLOW BEAN",
            "Starch": "GARLIC MASHED POTATO",
            "Dessert": "INDIAN PUDDING (MOLASSES/CORNMEAL)"
          },
          "Wednesday": {
            "Appetizer 1": "MANHATTAN CLAM CHOWDER (TOMATO BASE)",
            "Appetizer 2": "CLASSIC DEVILLED EGGS WITH BABY GREENS",
            "Elevated": "GRILLED TILAPIA",
            "Comfort": "TURKEY CUTLET WITH ARUGULA",
            "Alternative": "CARAMELIZED ONION TART",
            "Veggie 1": "GRILLED EGGPLANT CHUNKS",
            "Veggie 2": "ROASTED ZUCCHINI",
            "Starch": "BUTTERED HERB NOODLE",
            "Dessert": "BOSTON CREAM PIE"
          },
          "Thursday": {
            "Appetizer 1": "THAI CHICKEN NOODLE SOUP",
            "Appetizer 2": "WHITE BEAN DIP WITH TOASTED PITA CHIPS",
            "Elevated": "SAUTEED SHRIMP AND PESTO PASTA",
            "Comfort": "SALMON FILET WITH TZATZIKI SAUCE",
            "Alternative": "TOMATO CHEDDAR AND BACON PIE",
            "Veggie 1": "GRILLED ASPARAGUS",
            "Veggie 2": "SAUTEED BABY PEPPERS",
            "Starch": "STICKY JASMINE RICE",
            "Dessert": "ASSORTED DESSERTS"
          },
          "Friday": {
            "Appetizer 1": "RIBBON SALAD WITH ORANGE VINAIGRETTE",
            "Appetizer 2": "CREAM OF ASPARAGUS SOUP WITH SOUR CREAM",
            "Elevated": "BEEF STROGANOFF",
            "Comfort": "SEARED CATFISH",
            "Alternative": "CHICKEN CAESAR SALAD",
            "Veggie 1": "CARROT AND PEA MIX",
            "Veggie 2": "STEAMED CAULIFLOWER",
            "Starch": "CORNBREAD",
            "Dessert": "CLASSIC BUTTER TARTS"
          },
          "Saturday": {
            "Appetizer 1": "SMOKED SALMON & AVOCADO MOUSSE PLATE",
            "Appetizer 2": "ROASTED RED PEPPER SOUP",
            "Elevated": "DOVER SOLE WITH HERB OIL",
            "Comfort": "GRILLED LEMON GARLIC CHICKEN BREAST",
            "Alternative": "GRILLED VEGETABLE SKEWER",
            "Veggie 1": "GRILLED ZUCCHINI CHUNKS",
            "Veggie 2": "STEAMED CARROT WEDGES",
            "Starch": "FARO WITH FRESH HERBS",
            "Dessert": "SHOOFLY PIE"
          },
          "Sunday": {
            "Appetizer 1": "HUSH PUPPIES WITH GARLIC DIP",
            "Appetizer 2": "GRILLED EGGPLANT CAPRESE DISH",
            "Elevated": "BBQ PORK BACK RIBS",
            "Comfort": "CREAMY MAC N CHEESE",
            "Alternative": "CHICKEN MARSALA",
            "Veggie 1": "STEAMED GREEN BEANS",
            "Veggie 2": "ROASTED ROOT VEGETABLE",
            "Starch": "LOADED BAKED POTATO",
            "Dessert": "POUDING CHOMEUR"
          }
        }
      },
      "Week 4": {
        "days": {
          "Monday": {
            "Appetizer 1": "SHRIMP CEVICHE WITH CROSTINI AND SALSA",
            "Appetizer 2": "TOMATO PUFF TART",
            "Elevated": "JAMBALAYA",
            "Comfort": "CHICKEN BROCCOLI RICE CASSEROLE",
            "Alternative": "CORN SPOONBREAD",
            "Veggie 1": "ROASTED BROCCOLINI",
            "Veggie 2": "STEAMED CARROTS",
            "Starch": "ROASTED POTATO",
            "Dessert": "STRAWBERRY LEMONADE BARS"
          },
          "Tuesday": {
            "Appetizer 1": "LEMON ORZO SALAD",
            "Appetizer 2": "TARRAGON CHICKEN SALAD CROSTINI",
            "Elevated": "CHICKEN FRANCESE",
            "Comfort": "CLASSIC BEEF CHILI",
            "Alternative": "VEGETABLE ENCHILADAS",
            "Veggie 1": "ROASTED BUTTERNUT SQUASH",
            "Veggie 2": "SAUTEED PEPPERS",
            "Starch": "SPANISH RICE",
            "Dessert": "BLUEBERRY CRUMBLE CHEESECAKE"
          },
          "Wednesday": {
            "Appetizer 1": "GRILLED CLAMS WITH CUCUMBER AND SCALLION",
            "Appetizer 2": "MUFFULETTA OLIVE SALAD",
            "Elevated": "SMOTHERED PORK CHOPS IN MUSHROOM GRAVY",
            "Comfort": "FARFELLE PASTA WITH CHICKEN AND SAUSAGE",
            "Alternative": "GRILLED COD WITH ROMESCO SAUCE",
            "Veggie 1": "ROASTED BRUSSEL SPROUT WITH LEMON",
            "Veggie 2": "STEAMED GREEN BEANS",
            "Starch": "SWEET POTATO PUREE",
            "Dessert": "MARGARITA BARS"
          },
          "Thursday": {
            "Appetizer 1": "SUMMER RICE WRAPS",
            "Appetizer 2": "VIDALIA ONION SOUP",
            "Elevated": "GRILLED BEEF STEAK WITH GREEN PEPPERCORN SAUCE",
            "Comfort": "BAKED SALMON WITH BLACK BEAN SALSA",
            "Alternative": "BAKED CAULIFLOWER STEAK WITH CAJUN CORN SALSA",
            "Veggie 1": "SAUTEED SPINACH",
            "Veggie 2": "STEAMED CAULIFLOWER",
            "Starch": "BUTTER MASHED POTATO",
            "Dessert": "ASSORTED DESSERTS"
          },
          "Friday": {
            "Appetizer 1": "BROCCOLI CHEDDAR SOUP",
            "Appetizer 2": "WATERMELON FETA CUCUMBER SALAD",
            "Elevated": "PORK SCHNITZEL WITH CINNAMON APPLE SAUCE",
            "Comfort": "TURKEY POT ROAST",
            "Alternative": "GARLIC SAUTEED SHRIMP",
            "Veggie 1": "SEARED GREEN BEANS",
            "Veggie 2": "ROASTED ACORN SQUASH WEDGES",
            "Starch": "SPAETZLE",
            "Dessert": "PAVLOVA WITH FRESH BERRIES"
          },
          "Saturday": {
            "Appetizer 1": "TOMATO BASIL PIZETTE",
            "Appetizer 2": "SUMMER MINESTRONE",
            "Elevated": "SALISBURY STEAK IN ONION GRAVY",
            "Comfort": "OVEN BAKED BBQ BONE-IN CHICKEN",
            "Alternative": "ROASTED VEGETABLE AND FALAFEL ON BREAD",
            "Veggie 1": "RATATOUILLE COINS",
            "Veggie 2": "TRI COLOR CAULIFLOWER GRATIN",
            "Starch": "STEAMED CARROTS",
            "Dessert": "APEROL SPRITZ TRIFLE"
          },
          "Sunday": {
            "Appetizer 1": "CHICKEN GNOCCHI SOUP",
            "Appetizer 2": "CLASSIC POTATO SALAD",
            "Elevated": "LOBSTER TAIL THERMIDOR",
            "Comfort": "SPAGHETTI WITH BOLOGNESE",
            "Alternative": "",
            "Veggie 1": "SAUTEED SPINACH WITH GARROT/MUSHROOM/ONION",
            "Veggie 2": "PARMESAN GREEN BEANS",
            "Starch": "STEAMED BROCCOLI",
            "Dessert": "CHERRY SLAB PIE BARS"
          }
        }
      }
    }
  }
}
